ovos_skill_camera/LICENSE
ovos_skill_camera/MANIFEST.in
ovos_skill_camera/README.md
ovos_skill_camera/__init__.py
ovos_skill_camera/camera.wav
ovos_skill_camera/requirements.txt
ovos_skill_camera/version.py
ovos_skill_camera/locale/ca/camera_error.dialog
ovos_skill_camera/locale/ca/camera_yes.dialog
ovos_skill_camera/locale/ca/get_ready.dialog
ovos_skill_camera/locale/ca/have_camera.intent
ovos_skill_camera/locale/ca/picture.dialog
ovos_skill_camera/locale/ca/take_picture.intent
ovos_skill_camera/locale/da/camera_error.dialog
ovos_skill_camera/locale/da/camera_yes.dialog
ovos_skill_camera/locale/da/get_ready.dialog
ovos_skill_camera/locale/da/have_camera.intent
ovos_skill_camera/locale/da/picture.dialog
ovos_skill_camera/locale/da/take_picture.intent
ovos_skill_camera/locale/en-us/camera_error.dialog
ovos_skill_camera/locale/en-us/camera_yes.dialog
ovos_skill_camera/locale/en-us/get_ready.dialog
ovos_skill_camera/locale/en-us/have_camera.intent
ovos_skill_camera/locale/en-us/picture.dialog
ovos_skill_camera/locale/en-us/take_picture.intent
ovos_skill_camera/locale/fr-fr/camera_error.dialog
ovos_skill_camera/locale/fr-fr/camera_yes.dialog
ovos_skill_camera/locale/fr-fr/get_ready.dialog
ovos_skill_camera/locale/fr-fr/have_camera.intent
ovos_skill_camera/locale/fr-fr/picture.dialog
ovos_skill_camera/locale/fr-fr/take_picture.intent
ovos_skill_camera/locale/pt-pt/camera_error.dialog
ovos_skill_camera/locale/pt-pt/camera_yes.dialog
ovos_skill_camera/locale/pt-pt/get_ready.dialog
ovos_skill_camera/locale/pt-pt/have_camera.intent
ovos_skill_camera/locale/pt-pt/picture.dialog
ovos_skill_camera/locale/pt-pt/take_picture.intent
ovos_skill_camera/ovos_skill_camera.egg-info/PKG-INFO
ovos_skill_camera/ovos_skill_camera.egg-info/SOURCES.txt
ovos_skill_camera/ovos_skill_camera.egg-info/dependency_links.txt
ovos_skill_camera/ovos_skill_camera.egg-info/entry_points.txt
ovos_skill_camera/ovos_skill_camera.egg-info/requires.txt
ovos_skill_camera/ovos_skill_camera.egg-info/top_level.txt
ovos_skill_camera-1.0.4.dist-info/LICENSE
ovos_skill_camera-1.0.4.dist-info/METADATA
ovos_skill_camera-1.0.4.dist-info/WHEEL
ovos_skill_camera-1.0.4.dist-info/entry_points.txt
ovos_skill_camera-1.0.4.dist-info/top_level.txt
ovos_skill_camera-1.0.4.dist-info/RECORD
