Metadata-Version: 2.1
Name: ovos-skill-camera
Version: 1.0.4
Summary: OVOS camera skill
Home-page: https://github.com/OpenVoiceOS/ovos-skill-camera
Author: OpenVoiceOS
Author-email: jarbasai@mailfence.com
License: Apache-2.0
Keywords: ovos skill plugin
License-File: LICENSE
Requires-Dist: ovos-workshop>=0.0.12
